examples/demo.py
examples/theme_switcher.py
materialgui/__init__.py
materialgui/core/app.py
materialgui/core/style.py
materialgui/core/theme.py
materialgui/effects/ripple.py
materialgui/utils/icons.py
materialgui/widgets/__init__.py
materialgui/widgets/button.py
materialgui/widgets/card.py
materialgui/widgets/fab.py
materialgui/widgets/iconbutton.py
materialgui/widgets/textfield.py
materialgui-0.1.0.dist-info/licenses/LICENSE
tests/demo.py
tests/test_widgets.py
materialgui-0.1.0.dist-info/METADATA
materialgui-0.1.0.dist-info/WHEEL
materialgui-0.1.0.dist-info/top_level.txt
materialgui-0.1.0.dist-info/RECORD
