Metadata-Version: 2.4
Name: materialgui
Version: 0.1.0
Summary: Material Design GUI for Python
Requires-Python: >=3.8
License-File: LICENSE
Dynamic: license-file
